[
  {
    "repo": "react-aframe-volume-renderer",
    "site_name": "Volume Renderer",
    "authors": [
      {
        "name": "Camilo Diaz Rodriguez",
        "github_user": "kmilo9999"
      }
    ],
    "repo_url": "https://github.com/brown-ccv/react-aframe-volume-renderer",
    "site_description": "",
    "docs_url": null,
    "type": "software"
  },
  {
    "repo": "brown-ccv/ccv-status-frontend",
    "site_name": "Status Page",
    "authors": [
      {
        "name": "Fernando Gelin",
        "github_user": "fernandogelin"
      }
    ],
    "repo_url": "https://github.com/brown-ccv/ccv-status-frontend",
    "site_description": "Simple Ember application that uses the GitHub API as backend to display status of CCV Resources.",
    "type": "software"
  }
]